python_libmaas-0.6.8-nspkg.pth
maas/client/__init__.py
maas/client/enum.py
maas/client/errors.py
maas/client/facade.py
maas/client/bones/__init__.py
maas/client/bones/helpers.py
maas/client/flesh/__init__.py
maas/client/flesh/controllers.py
maas/client/flesh/devices.py
maas/client/flesh/fabrics.py
maas/client/flesh/files.py
maas/client/flesh/machines.py
maas/client/flesh/nodes.py
maas/client/flesh/profiles.py
maas/client/flesh/shell.py
maas/client/flesh/spaces.py
maas/client/flesh/subnets.py
maas/client/flesh/tables.py
maas/client/flesh/tabular.py
maas/client/flesh/tags.py
maas/client/flesh/users.py
maas/client/flesh/vlans.py
maas/client/utils/__init__.py
maas/client/utils/auth.py
maas/client/utils/creds.py
maas/client/utils/diff.py
maas/client/utils/maas_async.py
maas/client/utils/multipart.py
maas/client/utils/profiles.py
maas/client/utils/types.py
maas/client/viscera/__init__.py
maas/client/viscera/account.py
maas/client/viscera/bcache_cache_sets.py
maas/client/viscera/bcaches.py
maas/client/viscera/block_devices.py
maas/client/viscera/boot_resources.py
maas/client/viscera/boot_source_selections.py
maas/client/viscera/boot_sources.py
maas/client/viscera/controllers.py
maas/client/viscera/devices.py
maas/client/viscera/domains.py
maas/client/viscera/events.py
maas/client/viscera/fabrics.py
maas/client/viscera/files.py
maas/client/viscera/filesystem_groups.py
maas/client/viscera/filesystems.py
maas/client/viscera/interfaces.py
maas/client/viscera/ipranges.py
maas/client/viscera/logical_volumes.py
maas/client/viscera/maas.py
maas/client/viscera/machines.py
maas/client/viscera/nodes.py
maas/client/viscera/partitions.py
maas/client/viscera/pods.py
maas/client/viscera/raids.py
maas/client/viscera/resource_pools.py
maas/client/viscera/spaces.py
maas/client/viscera/sshkeys.py
maas/client/viscera/static_routes.py
maas/client/viscera/subnets.py
maas/client/viscera/tags.py
maas/client/viscera/users.py
maas/client/viscera/version.py
maas/client/viscera/vlans.py
python_libmaas-0.6.8.dist-info/LICENSE
python_libmaas-0.6.8.dist-info/METADATA
python_libmaas-0.6.8.dist-info/WHEEL
python_libmaas-0.6.8.dist-info/entry_points.txt
python_libmaas-0.6.8.dist-info/namespace_packages.txt
python_libmaas-0.6.8.dist-info/top_level.txt
python_libmaas-0.6.8.dist-info/RECORD
